Metadata-Version: 2.1
Name: tap-intacct
Version: 1.0.2
Summary: Singer.io tap for extracting data from Intacct
Home-page: http://singer.io
Author: Stitch
Classifier: Programming Language :: Python :: 3 :: Only
License-File: LICENSE
